[
  {
    "Products": [
      "SimpleHireMiniSet",
      "SimpleHireBigPack",
      "SpecialHireMiniSet",
      "SpecialHireSet",
      "ArenaTickets",
      "RedDastSet",
      "RaceHireStone",
      "FortuneCoinSet",
      "StoneReplacementProduct",
      "ContinuumStoneBigSet",
      "ForceStoneMiniSet",
      "ForceStoneBigSet"
    ],
    "RecoveryType": 1,
    "Promotions": [],
    "Id": "CityMarket"
  },
  {
    "Products": [
      "TicketOnArena"
    ],
    "RecoveryType": 5,
    "Promotions": [],
    "Id": "ResourceMarket"
  },
  {
    "Products": [
      "SweetCycleCoolWeapon",
      "SweetCycleGold",
      "SweetCycleContiunumStone"
    ],
    "RecoveryType": 4,
    "Promotions": [],
    "Id": "SweetCycleMarket"
  },
  {
    "Products": [
      "SweetCycleCoolWeapon",
      "SweetCycleGold",
      "SweetCycleContiunumStone"
    ],
    "RecoveryType": 3,
    "Promotions": [],
    "Id": "GuildMarket"
  }
]